data_importer/__init__.py
data_importer/admin.py
data_importer/forms.py
data_importer/listeners.py
data_importer/models.py
data_importer/tasks.py
data_importer/views.py
data_importer/core/__init__.py
data_importer/core/base.py
data_importer/core/default_settings.py
data_importer/core/descriptor.py
data_importer/core/exceptions.py
data_importer/django_migrations/0001_initial.py
data_importer/django_migrations/__init__.py
data_importer/importers/__init__.py
data_importer/importers/base.py
data_importer/importers/csv_importer.py
data_importer/importers/generic.py
data_importer/importers/xls_importer.py
data_importer/importers/xlsx_importer.py
data_importer/importers/xml_importer.py
data_importer/readers/__init__.py
data_importer/readers/csv_reader.py
data_importer/readers/xls_reader.py
data_importer/readers/xlsx_reader.py
data_importer/readers/xml_reader.py
data_importer/south_migrations/0001_initial.py
data_importer/south_migrations/0002_auto__add_field_filehistory_owner.py
data_importer/south_migrations/0003_auto__add_field_filehistory_is_task__add_field_filehistory_status.py
data_importer/south_migrations/0004_auto__del_field_filehistory_content__add_field_filehistory_filename.py
data_importer/south_migrations/0005_auto__add_filehistorylog.py
data_importer/south_migrations/__init__.py
data_importer/templates/data_importer.html
data_importer/templates/my_upload.html
data_importer-3.1.5.dist-info/LICENSE
data_importer-3.1.5.dist-info/METADATA
data_importer-3.1.5.dist-info/WHEEL
data_importer-3.1.5.dist-info/top_level.txt
data_importer-3.1.5.dist-info/RECORD
