Metadata-Version: 2.1
Name: data-importer
Version: 3.1.5
Summary: Simple library to easily import data with Django
Home-page: https://github.com/valdergallo/data-importer
Author: valdergallo
Author-email: valdergallo@gmail.com
License: BSD
Download-URL: https://github.com/valdergallo/data-importer/tarball/3.1.5/
Keywords: Django Data Importer XLS XLSX CSV XML
Platform: any
Classifier: Framework :: Django
Classifier: Operating System :: OS Independent
Classifier: Topic :: Utilities
Requires-Dist: django (>=1.4)
Requires-Dist: openpyxl (>=2.4.0)
Requires-Dist: xlrd (>=1.0.0)
